protollm_sdk/__init__.py
protollm_sdk/celery/app.py
protollm_sdk/celery/config.py
protollm_sdk/celery/constants.py
protollm_sdk/celery/job.py
protollm_sdk/config.py
protollm_sdk/jobs/__init__.py
protollm_sdk/jobs/job.py
protollm_sdk/jobs/job_context.py
protollm_sdk/jobs/job_invoke.py
protollm_sdk/jobs/llm_api.py
protollm_sdk/jobs/outer_llm_api.py
protollm_sdk/jobs/result_storage.py
protollm_sdk/jobs/text_embedder.py
protollm_sdk/jobs/utility.py
protollm_sdk/jobs/vector_db.py
protollm_sdk/models/__init__.py
protollm_sdk/models/errors.py
protollm_sdk/models/job_context_models.py
protollm_sdk/object_interface/__init__.py
protollm_sdk/object_interface/rabbit_mq_wrapper.py
protollm_sdk/object_interface/redis_wrapper.py
protollm_sdk/utils/__init__.py
protollm_sdk/utils/reddis.py
protollm_sdk/utils/singleton.py
protollm_sdk-1.2.0.dist-info/METADATA
protollm_sdk-1.2.0.dist-info/WHEEL
protollm_sdk-1.2.0.dist-info/RECORD
